{
  "devices": {
    "28:f7:d6:af:62:01": {
      "ip": "192.168.0.1",
      "mac": "28:f7:d6:af:62:01",
      "type": "Unknown Device",
      "vendor": "Unknown",
      "hostname": "_gateway",
      "open_ports": [
        {
          "port": 80,
          "service": "HTTP"
        },
        {
          "port": 443,
          "service": "HTTPS"
        }
      ],
      "last_seen": "2026-01-02T22:11:30.420660",
      "first_seen": "2025-12-29T19:59:39.075591"
    },
    "40:ac:bf:3e:53:af": {
      "ip": "192.168.0.104",
      "mac": "40:ac:bf:3e:53:af",
      "type": "Security Camera",
      "vendor": "Hikvision",
      "hostname": "Hikvision-Camera-104",
      "open_ports": [
        {
          "port": 8443,
          "service": "HTTPS-Alt"
        }
      ],
      "last_seen": "2026-01-02T22:11:38.028476",
      "first_seen": "2026-01-02T22:03:15.212678"
    },
    "40:ac:bf:37:d6:39": {
      "ip": "192.168.0.102",
      "mac": "40:ac:bf:37:d6:39",
      "type": "Security Camera",
      "vendor": "Hikvision",
      "hostname": "Hikvision-Camera-102",
      "open_ports": [
        {
          "port": 8443,
          "service": "HTTPS-Alt"
        }
      ],
      "last_seen": "2026-01-02T22:11:40.158622",
      "first_seen": "2026-01-02T22:03:17.589772"
    },
    "84:46:93:6d:3c:3f": {
      "ip": "192.168.0.100",
      "mac": "84:46:93:6d:3c:3f",
      "type": "Android Phone",
      "vendor": "Xiaomi",
      "hostname": "Xiaomi-Phone-100",
      "open_ports": [],
      "last_seen": "2026-01-02T22:11:42.286279",
      "first_seen": "2026-01-02T22:03:13.129609"
    },
    "48:35:2b:cb:48:0a": {
      "ip": "192.168.0.109",
      "mac": "48:35:2b:cb:48:0a",
      "type": "Unknown Device",
      "vendor": "Unknown",
      "hostname": "Unknown-109",
      "open_ports": [],
      "last_seen": "2026-01-02T22:11:44.454943",
      "first_seen": "2026-01-02T22:03:19.830129"
    }
  },
  "last_scan_time": "2026-01-02T22:11:44.454986"
}